zeblok/__init__.py
zeblok/api.py
zeblok/auth.py
zeblok/deploy.py
zeblok/errors.py
zeblok/microservice.py
zeblok/pipeline.py
zeblok/utils.py
zeblok_py-0.0.8.dist-info/LICENSE.md
zeblok_py-0.0.8.dist-info/METADATA
zeblok_py-0.0.8.dist-info/WHEEL
zeblok_py-0.0.8.dist-info/top_level.txt
zeblok_py-0.0.8.dist-info/RECORD
